{
  "id": "2218eea5-49cc-40cc-8ce6-02801b8a5c3d",
  "slug": "patent-infringement-analysis-report",
  "name": "Patent Infringement Analysis Report",
  "summary": "Generates a comprehensive technical and legal report analyzing patent infringement by mapping patent claims to features of an accused product or process via claim charts. Evaluates literal infringement and doctrine of equivalents under U.S. patent law principles like Phillips claim construction. Use for IP litigation counsel, in-house teams, or experts assessing litigation, licensing, or settlement strategies.",
  "content": "# Patent Infringement Analysis Report\n\nYou are tasked with preparing a comprehensive Patent Infringement Analysis Report that provides a thorough technical and legal evaluation of whether an accused product or process infringes one or more claims of an asserted patent. This report must be suitable for use by patent litigation counsel, in-house legal teams, or technical experts, and should support strategic decision-making regarding potential litigation, licensing negotiations, or settlement discussions.\n\nYour analysis must be methodical, objective, and grounded in established patent law principles, including the framework for claim construction established in Phillips v. AWH Corp. and the standards for infringement analysis under 35 U.S.C. \u00a7 271. Throughout your analysis, maintain a neutral, analytical tone that acknowledges both strengths and weaknesses in the infringement position.\n\n## Initial Document Review and Evidence Gathering\n\nBefore beginning your substantive analysis, conduct a comprehensive review of all available materials related to the patent and accused product. Search through all uploaded documents to identify and extract the complete patent specification, file history, prosecution documents, and any amendments or office action responses that may inform claim construction. Locate technical documentation for the accused product, including product specifications, user manuals, marketing materials, technical drawings, photographs, schematics, source code excerpts, or reverse engineering reports. Identify any prior art references, technical standards, or industry publications that may be relevant to understanding the technology or assessing validity. Extract specific factual details including patent numbers, filing dates, issue dates, inventor names, assignee information, claim language, product model numbers, technical specifications, and any statements made during prosecution that could constitute disclaimer or estoppel.\n\nWhen gathering this information, pay particular attention to the exact language used in the patent claims, as even subtle differences in terminology can be dispositive. Note any special definitions provided in the specification where the patentee may have acted as their own lexicographer. Identify portions of the prosecution history where claim scope may have been narrowed through amendment or argument. For the accused product, focus on technical features that appear to correspond to claim limitations, documenting the evidence source for each feature with precise citations to page numbers, section references, figure numbers, or line numbers that will support your subsequent claim chart analysis.\n\n## Executive Summary\n\nBegin with a concise executive summary that distills the entire analysis into key takeaways for busy decision-makers who may not read the full report. This section should immediately communicate your overall conclusion regarding infringement likelihood, expressed with appropriate qualifications such as \"strong likelihood of infringement,\" \"probable infringement,\" \"unlikely to infringe,\" or \"no infringement.\" Identify which specific claims are at issue and provide your bottom-line assessment for each independent claim and any particularly significant dependent claims.\n\nPresent your principal recommendations regarding next steps, which may include ceasing allegedly infringing activities, seeking a license, preparing for litigation, conducting further technical investigation, pursuing design-around options, or initiating post-grant proceedings. Highlight any critical risks, time-sensitive considerations, or threshold legal issues that require immediate attention, such as potential willful infringement exposure, upcoming statute of limitations deadlines, or ongoing related litigation. Flag any significant uncertainties in your analysis that stem from ambiguous claim language, missing technical information about the accused product, or unsettled legal questions that could materially affect the outcome.\n\nThis summary should be written in clear, accessible language while maintaining technical and legal precision, and should not exceed two pages. Structure it to allow a reader to understand the core conclusion, the primary basis for that conclusion, the key risks and uncertainties, and the recommended course of action without needing to review the detailed analysis that follows.\n\n## Patent Overview and Background\n\nProvide a comprehensive overview of the asserted patent that establishes the necessary foundation for your infringement analysis. Begin with the complete bibliographic information including the patent number, title, issue date, filing date, priority date if claiming foreign or domestic priority, inventors, original assignee, current assignee or owner, and any related patent family members including continuations, divisionals, continuations-in-part, or foreign counterparts that may be relevant to understanding the technology or prosecution history.\n\nDescribe the technical field of the invention by identifying the relevant industry, technology area, and specific problem or need that the patent addresses according to its background section. Summarize the disclosed invention by explaining the fundamental concept, how the invention operates, what components or steps are involved, and what advantages or improvements the patent specification attributes to the invention over prior art. Draw this characterization directly from the specification's summary and detailed description, using representative quotes where helpful to capture the patentee's own description of the invention.\n\nReview the patent's prosecution history to identify any amendments made to the claims, arguments presented to overcome rejections, prior art cited and distinguished, or statements about claim scope that could inform claim construction through prosecution disclaimer or estoppel. Note whether any claims were canceled, whether claim language was narrowed to overcome prior art or written description rejections, and whether the applicant made any statements characterizing the invention or distinguishing it from prior art that could limit the scope of claim terms. If the prosecution history is voluminous, focus on amendments and arguments related to the specific claim limitations that are most relevant to the infringement analysis.\n\nIdentify the specific claims being asserted in this analysis, distinguishing between independent and dependent claims and noting the dependency relationships. Explain why these particular claims were selected for assertion, whether based on their breadth, their specific coverage of the accused product's features, or strategic considerations. Note the patent's current legal status, including whether it has been involved in any litigation, whether any post-grant proceedings such as inter partes review, post-grant review, or ex parte reexamination have been filed or completed, whether any claims have been held unpatentable or invalid, and whether any terminal disclaimers have been filed that could affect damages or enforcement.\n\n## Claim Construction Analysis\n\nConduct a detailed claim construction analysis for each disputed or significant claim term, recognizing that claim construction is the essential first step in any infringement analysis and often determines the outcome. Apply the principles established in Phillips v. AWH Corp., which requires giving claim terms their ordinary and customary meaning as understood by a person of ordinary skill in the art at the time of the invention, informed primarily by intrinsic evidence.\n\nFor each term requiring construction, begin by examining the claim language itself to understand how the term is used in the context of the claim as a whole and in relation to other claims. Analyze the specification to determine how it describes, defines, exemplifies, or uses the term, recognizing that the specification is the single best guide to the meaning of a disputed term and that it may reveal whether the patentee intended a special definition different from the ordinary meaning. Search the specification for explicit definitions, statements that \"as used herein\" a term means something specific, or consistent usage that demonstrates a clear intent to define the term in a particular way.\n\nExamine the prosecution history for any statements, amendments, or arguments that may limit claim scope through prosecution disclaimer or estoppel. Identify instances where the applicant amended claims to overcome prior art, distinguished prior art based on the presence or absence of certain features, or made arguments about claim scope to secure allowance. Determine whether these prosecution events would lead a reasonable examiner or competitor to conclude that the applicant surrendered certain claim scope or disclaimed coverage of particular embodiments.\n\nConsider the context provided by other claims in the patent, applying the doctrine of claim differentiation where appropriate to presume that different claims have different scope and that limitations appearing in dependent claims should not be read into independent claims absent clear indication otherwise. However, recognize that claim differentiation is not a hard rule and cannot overcome clear disclaimer in the specification or prosecution history.\n\nWhere appropriate, consider extrinsic evidence such as expert testimony about the understanding of persons of ordinary skill in the art, technical dictionaries, treatises, or prior art references that illuminate the meaning of technical terms. However, give extrinsic evidence less weight than intrinsic evidence and use it primarily to confirm or clarify the meaning derived from the claims, specification, and prosecution history rather than to contradict or supplant it.\n\nPresent your construction for each term in clear, precise language that can be directly applied in the infringement analysis. Format your constructions in a table or structured list that identifies the claim term, your proposed construction, and a concise explanation of the reasoning and evidence supporting that construction with specific citations to the specification (by column and line number or paragraph), prosecution history (by document date and page), or other sources. Where claim terms are ambiguous or multiple reasonable constructions exist, acknowledge this uncertainty explicitly, explain the competing constructions and their respective support, and analyze how each alternative construction would affect the infringement analysis. This transparency about uncertainty is critical for informed decision-making.\n\nAddress any means-plus-function limitations under 35 U.S.C. \u00a7 112(f) by identifying the claimed function, locating the corresponding structure in the specification that performs that function, and determining whether the specification adequately discloses structure rather than merely describing the function in different words. Note that means-plus-function claiming significantly narrows claim scope to the disclosed structure and equivalents thereof.\n\n## Description of Accused Product or Process\n\nProvide a thorough technical description of the accused product, process, method, or system that allegedly infringes the asserted patent claims. This description must be sufficiently detailed and precise to enable element-by-element comparison with the patent claims in your subsequent infringement analysis. Begin with an overview that identifies what the accused product is, its commercial name and model number, its intended purpose and function, its target market, and how it operates at a high level to provide context for the detailed technical analysis that follows.\n\nSystematically describe the relevant technical features, components, structures, materials, dimensions, or method steps that correspond to claim elements, organizing this description to parallel the structure of the asserted claims where possible. Use technical terminology that aligns with the claim language when the accused product includes features that appear to correspond to claimed elements, but maintain technical accuracy and avoid conclusory characterizations. For structural claims, describe the physical components, their arrangement, their interconnections, and how they function together. For method claims, describe the sequence of steps, what actions are performed, what materials or inputs are used, and what results are achieved.\n\nSupport your description with specific citations to technical documentation, including product specifications with page and section numbers, user manuals with version numbers and page references, marketing materials with publication dates, technical drawings with figure numbers, photographs with dates and sources, schematics with reference numerals, source code with file names and line numbers, or reverse engineering reports with test dates and methodologies. When relying on publicly available information, note the source and date to establish that the information is admissible evidence rather than speculation. When technical details are not publicly available, identify what information is missing, explain why it is relevant to the infringement analysis, and note that discovery, testing, inspection, or expert analysis may be required to fully characterize these features.\n\nIf the accused product has multiple versions, models, configurations, or generations, clarify which specific embodiments are being analyzed and document any material differences between versions that could affect the infringement analysis. Consider whether older versions, newer versions, or variants may infringe different claims or may avoid infringement through design changes. If the accused product is customizable or configurable by users, address whether infringement occurs in the default configuration, in common configurations, or only in specific configurations, as this may affect the theory of infringement and potential defenses.\n\nIdentify any aspects of the accused product's operation that are not apparent from external observation, such as internal algorithms, software logic, data structures, or processing steps that may be relevant to method claims or system claims with functional limitations. Note where additional technical investigation through reverse engineering, testing, or expert analysis would strengthen the infringement case by confirming the presence of non-obvious features.\n\n## Element-by-Element Infringement Analysis\n\nConduct a rigorous element-by-element infringement analysis using detailed claim charts that map each limitation of the asserted claims to corresponding features of the accused product or process. For each asserted claim, create a comprehensive claim chart formatted with columns for the claim element or limitation as properly construed, the corresponding feature or characteristic of the accused product with specific citations to evidence, and your analysis of whether the limitation is met literally or under the doctrine of equivalents.\n\nBegin by parsing each claim into its individual elements or limitations, ensuring that you identify every structural component, functional requirement, relational term, or method step recited in the claim. Number or label each limitation to facilitate clear reference in your analysis. Apply your claim constructions from the previous section to ensure that you are analyzing infringement based on the proper scope of each term rather than on an overly broad or narrow interpretation.\n\nAddress literal infringement first for each limitation, determining whether the accused product contains each and every claim limitation exactly as claimed or within the scope of the properly construed claim language. Remember that literal infringement requires that every single limitation be met; if even one limitation is absent from the accused product, there is no literal infringement of that claim under the all-elements rule. For each limitation, cite specific evidence from the accused product description, including document names, page numbers, figure references, or technical specifications that demonstrate the presence of the claimed feature. Use precise technical language and avoid conclusory statements; instead of stating \"the accused product includes element X,\" explain what specific component or feature of the accused product corresponds to element X and why it falls within the scope of the claim limitation as construed.\n\nFor limitations that are not literally met, analyze whether infringement exists under the doctrine of equivalents by applying the function-way-result test or the insubstantial differences test. Under the function-way-result test, determine whether the corresponding feature in the accused product performs substantially the same function in substantially the same way to achieve substantially the same result as the claimed limitation. Under the insubstantial differences test, assess whether the differences between the claimed limitation and the accused product's feature are insubstantial from the perspective of a person of ordinary skill in the art. Consider whether the accused product's feature is an obvious variation of the claimed limitation that any skilled artisan would recognize as an equivalent.\n\nHowever, recognize that the doctrine of equivalents is subject to important limitations that may preclude its application. Analyze whether prosecution history estoppel bars equivalents for any limitation where the applicant narrowed the claim through amendment to overcome prior art or to satisfy statutory requirements, as such amendments may create a presumption that the applicant surrendered the territory between the original claim scope and the amended claim scope. Consider whether the presumption of surrender can be rebutted by showing that the amendment was tangential to the equivalent in question, that there was some other reason to believe the patentee could not reasonably have been expected to describe the equivalent, or that the rationale for the amendment bore no relationship to the equivalent.\n\nAssess whether the doctrine of equivalents would vitiate any claim limitation entirely, which is impermissible because it would effectively eliminate that limitation from the claim. Determine whether the accused product's feature was disclosed in the specification but not claimed, which may indicate dedication to the public domain under Johnson & Johnston. Apply the all-limitations rule to ensure that the doctrine of equivalents is applied to individual limitations rather than to the invention as a whole.\n\nFor any means-plus-function limitations, ensure your analysis identifies the corresponding structure disclosed in the specification for performing the claimed function, compares that structure to the structure in the accused product that performs the same function, and determines whether the accused product's structure is identical or equivalent to the disclosed structure. Remember that equivalents in the means-plus-function context are limited to structures that perform the function in substantially the same way, which is a narrower test than the general doctrine of equivalents.\n\nAddress both independent and dependent claims in your analysis. For dependent claims, incorporate by reference your analysis of the independent claim from which they depend, then analyze the additional limitations added by the dependent claim. Note that dependent claims may be infringed even if independent claims are not, though this is rare in practice because dependent claims incorporate all limitations of their parent claims.\n\nProvide separate analyses for different theories of infringement as appropriate. Address direct infringement under 35 U.S.C. \u00a7 271(a), which requires that a single entity performs or uses each and every claim limitation. If direct infringement by a single party is not clear, consider indirect infringement theories under \u00a7 271(b) for inducement of infringement or \u00a7 271(c) for contributory infringement. For inducement, analyze whether the accused infringer actively induced others to directly infringe through actions such as providing instructions, marketing materials, or technical support that encourage infringing use, and whether the accused infringer had knowledge of the patent and specific intent to encourage infringement. For contributory infringement, determine whether the accused product is a component of a patented invention, whether it constitutes a material part of the invention, whether it has substantial non-infringing uses, and whether the accused infringer knew that the component was especially made or adapted for infringing use.\n\nConclude each claim analysis with a clear statement of your opinion on infringement likelihood, appropriately qualified based on the strength of the evidence and any uncertainties. Use precise language such as \"strong likelihood of literal infringement,\" \"probable infringement under the doctrine of equivalents,\" \"unlikely to infringe due to absence of limitation X,\" or \"no infringement because limitations Y and Z are not met.\" Explain the basis for your confidence level, noting which limitations are clearly met, which are met but with some uncertainty, and which are not met or are highly uncertain.\n\n## Patent Validity Considerations\n\nAssess potential validity challenges that could serve as defenses to infringement or inform strategic decisions, recognizing that while validity is technically a separate issue from infringement, validity considerations often significantly impact the overall risk assessment and settlement value of patent disputes. Note that issued patents are presumed valid under 35 U.S.C. \u00a7 282 and that an accused infringer must prove invalidity by clear and convincing evidence in district court litigation, though the lower preponderance standard applies in post-grant proceedings before the Patent Trial and Appeal Board.\n\nAnalyze whether the asserted claims may be invalid as anticipated under 35 U.S.C. \u00a7 102 by identifying prior art references such as patents, published patent applications, technical publications, products, public uses, or sales that may disclose each and every limitation of the claims. Search for prior art that predates the patent's effective filing date, considering both prior art that was cited during prosecution and prior art that was not before the examiner. For each potentially anticipatory reference, create an element-by-element comparison similar to your infringement analysis, mapping each claim limitation to disclosures in the prior art reference. Determine whether a single reference discloses every limitation either explicitly or inherently, and whether the reference enables a person of ordinary skill in the art to practice the claimed invention. Consider whether any prior art was publicly available or on sale more than one year before the patent's filing date, which could trigger the statutory bar provisions.\n\nEvaluate whether the claims may be obvious under 35 U.S.C. \u00a7 103 by considering whether the differences between the claimed invention and the prior art would have been obvious to a person of ordinary skill in the art at the time of the invention. Apply the Graham factors by determining the scope and content of the prior art, ascertaining the differences between the prior art and the claims, resolving the level of ordinary skill in the art, and considering objective indicia of non-obviousness such as commercial success, long-felt but unmet need, failure of others, copying, unexpected results, or industry praise. Identify combinations of prior art references that together may teach or suggest all claim limitations, and analyze whether a person of ordinary skill would have had reason to combine the references and a reasonable expectation of success in doing so. Consider whether the patent specification or prosecution history provides evidence of unexpected results or criticizes the prior art in ways that may support non-obviousness.\n\nAddress any potential subject matter eligibility issues under 35 U.S.C. \u00a7 101 if the claims are directed to abstract ideas, natural phenomena, laws of nature, or natural products. Apply the two-step Alice/Mayo framework by first determining whether the claims are directed to a patent-ineligible concept, and if so, whether the claims contain an inventive concept that transforms the claim into patent-eligible subject matter. This analysis is particularly important for software patents, business method patents, diagnostic method patents, or biotechnology patents where eligibility challenges are common.\n\nConsider potential invalidity challenges under 35 U.S.C. \u00a7 112, including whether the specification provides adequate written description to show that the inventor possessed the full scope of the claimed invention at the time of filing, whether the specification enables a person of ordinary skill in the art to make and use the full scope of the claimed invention without undue experimentation, and whether the claims are sufficiently definite to inform the public of the scope of protection with reasonable certainty. Analyze whether functional claiming, means-plus-function limitations, or broad claim language may create written description or enablement issues, particularly for dependent claims that broaden the scope of independent claims or for claims that cover a genus when the specification discloses only species.\n\nNote any prior art that was not considered during prosecution, as such art may be particularly relevant for invalidity contentions in litigation or for petitions for inter partes review, which have a lower burden of proof and may provide a faster, less expensive path to invalidating problematic claims. Identify the most significant validity concerns and assess their strength, considering both the legal standards and the quality of available evidence. Explain how these validity concerns affect the overall risk assessment, recognizing that strong invalidity defenses may reduce settlement value, discourage litigation, or provide leverage in licensing negotiations even if infringement is clear.\n\n## Potential Defenses, Risks, and Strategic Considerations\n\nIdentify and evaluate potential defenses beyond non-infringement and invalidity that may be available to an accused infringer or that may affect the patent owner's enforcement position. Consider equitable defenses such as laches, which bars recovery of pre-filing damages if the patent owner unreasonably delayed bringing suit and the accused infringer was materially prejudiced by the delay. Analyze whether the patent owner had knowledge of the accused infringement for an extended period before filing suit, whether the delay was reasonable under the circumstances, and whether the accused infringer relied on the patent owner's inaction by making substantial investments in the accused product.\n\nEvaluate equitable estoppel, which may bar enforcement if the patent owner engaged in misleading conduct that induced the accused infringer to reasonably believe it would not be sued for infringement, and the accused infringer relied on that conduct to its detriment. Consider whether any communications, licenses, or business relationships between the parties could support an estoppel defense. Assess whether an implied license may exist based on the parties' conduct, prior dealings, or the circumstances of how the accused infringer obtained the accused product, particularly if the accused product was purchased from an authorized source or incorporates components supplied by the patent owner.\n\nAnalyze patent exhaustion principles to determine whether the first sale doctrine limits the patent owner's rights, particularly if the accused infringement involves repair, refurbishment, or resale of products that were lawfully made and sold. Consider whether any prior licenses, covenants not to sue, settlement agreements, or release agreements may affect the parties' rights, and review the scope of any such agreements to determine whether they cover the accused product or the accused infringer's activities.\n\nEvaluate potential unenforceability defenses based on inequitable conduct during prosecution if evidence suggests that the applicant or prosecution counsel made material misrepresentations to the USPTO, withheld material prior art, or submitted false declarations with intent to deceive the examiner. Recognize that inequitable conduct is an extraordinary remedy that renders the entire patent unenforceable and requires proof of both materiality and intent by clear and convincing evidence, making it difficult to prove but potentially devastating if successful.\n\nConsider the impact of any ongoing or potential post-grant proceedings such as inter partes review, post-grant review, or ex parte reexamination on the litigation timeline and strategy. Note that district courts often stay litigation pending resolution of parallel USPTO proceedings, that inter partes review has a high rate of invalidating at least some challenged claims, and that estoppel provisions may limit the accused infringer's ability to raise certain invalidity arguments in litigation after an unsuccessful inter partes review.\n\nAssess damages-related issues that may affect the value of the dispute and settlement negotiations. Analyze whether the patent owner would be entitled to lost profits damages by showing that it makes and sells a competing product, that there is demand for the patented product, that it has manufacturing and marketing capability to meet demand, and that there are no acceptable non-infringing substitutes. If lost profits are not available, consider the reasonable royalty that would result from a hypothetical negotiation between the parties, taking into account the Georgia-Pacific factors, the importance of the patented feature to the accused product, the availability of design-arounds, and the strength of the patent.\n\nEvaluate whether the entire market value rule or apportionment principles would limit damages to the value attributable to the patented feature rather than the entire accused product, particularly for patents covering components or features of multi-component products. Consider whether the patent owner complied with the marking requirements of 35 U.S.C. \u00a7 287 by marking its own products with the patent number, as failure to mark may preclude recovery of pre-notice damages. Assess whether laches may limit the damages period even if it does not bar the suit entirely.\n\nIdentify risks associated with willful infringement findings, which could support enhanced damages up to three times the compensatory damages and an award of attorneys' fees to the prevailing party. Analyze whether the accused infringer had knowledge of the patent before the infringement began, whether it had a good-faith basis to believe it did not infringe or that the patent was invalid, and whether obtaining an opinion of counsel regarding non-infringement or invalidity would be advisable to demonstrate good faith and negate willfulness. Note that while opinions of counsel are no longer required to avoid adverse inferences regarding willfulness after Knorr-Bremse, they remain valuable evidence of good faith.\n\nEvaluate forum selection considerations if litigation appears likely, including potential venues where the patent owner might file suit based on the location of the accused infringer's principal place of business, where the accused infringer has regular and established places of business, or where acts of infringement occurred. Consider the relative advantages of different venues in terms of their patent-friendliness, speed to trial, local rules, judicial expertise in patent cases, and jury pools. Assess whether filing a declaratory judgment action in a preferred forum might provide strategic advantages in controlling the litigation venue and timing.\n\nAddress practical business considerations that may be as important as the legal analysis in determining the appropriate course of action. Evaluate the cost and duration of potential litigation, recognizing that patent litigation typically costs millions of dollars and takes two to three years to reach trial, compared to the potential damages exposure and the commercial importance of the accused product. Assess the commercial importance of the accused product to the accused infringer's business, including its revenue contribution, profit margins, strategic value, and whether design-around alternatives are technically and commercially feasible.\n\nConsider the strength of the patent owner's enforcement history and litigation track record, including whether it has successfully enforced the patent against other parties, whether it has lost any prior litigation or post-grant proceedings involving the patent, and whether it appears to be a practicing entity that competes in the market or a non-practicing entity focused on licensing and litigation. Evaluate the patent owner's financial resources and motivation to pursue litigation, as well as any reputational and relationship considerations between the parties that may favor settlement over adversarial litigation.\n\nAnalyze potential design-around solutions and their technical and commercial feasibility, including the engineering effort required, the impact on product performance or cost, the time required to implement and bring to market, and whether design-around options would themselves raise infringement concerns with other patents. Consider whether pursuing a license may be more cost-effective than litigation or design-around, and what a reasonable royalty rate might be based on industry standards, comparable licenses, and the value of the patented technology.\n\n## Conclusion and Strategic Recommendations\n\nSynthesize your analysis into clear, actionable conclusions and recommendations tailored to your client's specific situation and objectives. Restate your overall assessment of infringement likelihood for each asserted claim, integrating your claim construction analysis, element-by-element infringement findings, and validity considerations into a coherent bottom-line opinion expressed with appropriate confidence levels. Provide a candid evaluation of the strengths and weaknesses of both the infringement case and potential defenses, including any uncertainties or areas requiring further investigation such as missing technical information, ambiguous claim terms, or unsettled legal questions.\n\nRecommend specific next steps prioritized by urgency, cost-effectiveness, and likelihood of success. If the analysis reveals a strong likelihood of infringement with weak invalidity defenses, consider recommending that the accused infringer pursue design modifications to avoid infringement, seek a license through negotiation, or prepare for litigation by developing robust invalidity contentions and conducting comprehensive prior art searches. If the infringement case appears weak or validity defenses appear strong, consider recommending that the patent owner be put on notice of non-infringement and invalidity positions, that a declaratory judgment action be considered to resolve the dispute proactively, or that inter partes review be filed to challenge weak claims.\n\nIf further investigation is needed before a confident recommendation can be made, identify the specific information gaps and recommend concrete steps to fill them, such as conducting reverse engineering or testing of the accused product to confirm the presence or absence of specific features, obtaining expert opinions on claim construction or technical issues, conducting comprehensive prior art searches to identify the best invalidity references, or seeking discovery through litigation or pre-suit investigation to access non-public technical information.\n\nProvide a realistic assessment of the costs, timeline, and risks associated with each recommended course of action. For litigation, estimate the likely cost range based on the complexity of the technology and the number of asserted claims, the expected timeline from filing through trial and appeals, the probability of success on infringement and validity issues, the potential damages exposure or recovery, and the risk of adverse fee awards or enhanced damages. For licensing negotiations, suggest a reasonable royalty range based on comparable licenses and the strength of the infringement and validity positions, and recommend negotiation strategies. For design-around efforts, estimate the engineering cost and timeline, assess the technical and commercial risks, and evaluate whether the design-around would clearly avoid infringement.\n\nIf you are recommending against pursuing or defending an infringement claim, clearly explain the basis for this recommendation, whether it is the weakness of the infringement case, the strength of invalidity defenses, the disproportionate cost relative to the value at stake, or business considerations that favor avoiding confrontation. Ensure that your recommendations account for both legal and business considerations, recognizing that patent disputes are ultimately resolved through a combination of legal rights, commercial realities, and strategic objectives.\n\nClose with any time-sensitive actions that should be taken immediately to preserve rights, avoid increased damages exposure, or maintain strategic advantage. This may include ceasing potentially infringing activities to avoid willfulness findings, implementing document preservation procedures in anticipation of litigation, obtaining opinion of counsel before the next product shipment, filing for inter partes review before the one-year deadline after being served with a complaint, or initiating licensing discussions before the patent owner files suit.\n\n## Formatting and Documentation Requirements\n\nThroughout this report, maintain precise citations to all evidence using a consistent citation format. For patent documents, cite by patent number, column and line number for specifications, and claim number for claims. For prosecution history documents, cite by document type, date, and page number. For technical specifications and product documentation, cite by document title, version or publication date, and page or section number. For legal authorities, provide full case citations in Bluebook format including case name, reporter volume and page, court, and year.\n\nStructure the report professionally with a table of contents listing all major sections and subsections with page numbers, numbered sections and subsections for easy reference, headers and footers with the report title and page numbers, and a clear visual hierarchy using headings, subheadings, and formatting. Include appendices for detailed claim charts, copies of relevant patent claims, key prosecution history documents, technical drawings or photographs of the accused product, and any other supporting exhibits referenced in the analysis.\n\nUse clear, professional language that is accessible to both legal and technical audiences, explaining technical concepts with sufficient context for non-experts while maintaining precision for technical readers, and explaining legal concepts with sufficient background for non-lawyers while maintaining accuracy for legal readers. Where technical concepts require explanation, provide sufficient context without oversimplifying or talking down to the reader. Acknowledge limitations in your analysis, areas of uncertainty, and any assumptions you have made, as transparency about what is known and unknown is critical for informed decision-making.\n\nThe final report should be comprehensive yet focused, typically ranging from twenty to fifty pages depending on the complexity of the technology, the number of asserted claims, the volume of prior art, and the number of accused products, but should not include unnecessary length for its own sake. Every section should add value to the analysis and support the ultimate conclusions and recommendations. The report should be suitable for use by litigation counsel in developing case strategy, by business decision-makers in evaluating settlement or licensing options, and by technical experts in understanding the infringement and validity issues.",
  "parent_skill_id": "adccc2a5-9c43-42a4-8e4e-70541b15086f",
  "skill_type": "form",
  "visibility": "public",
  "legal_context": {
    "complexity": "senior",
    "industries": [],
    "party_roles": [
      "neutral"
    ],
    "skill_modes": [
      "analysis"
    ],
    "court_systems": [],
    "jurisdictions": [
      "US"
    ],
    "matter_phases": [
      "pre-filing",
      "discovery"
    ],
    "document_types": [
      "analysis"
    ],
    "practice_areas": [
      "Litigation"
    ],
    "sub_practice_areas": [
      "intellectual-property-litigation"
    ]
  },
  "version": 1,
  "author_name": null,
  "license": "Apache-2.0",
  "created_at": "2026-01-06T03:27:03.831435",
  "updated_at": "2026-02-22T21:37:47.543804"
}