{
  "id": "21d8250b-370c-4c3a-becf-010dfa96d123",
  "slug": "personal-injury-medical-treatment-summary",
  "name": "Medical Treatment Summary",
  "summary": "Generates a narrative summary of medical treatments in personal injury litigation, translating complex medical jargon into accessible, persuasive prose that explains injuries, treatment rationale, and client prognosis. Highlights the impact on the client's daily life to complement chronologies and support damages arguments. Use it for insurance negotiations, motions, or trial preparation where medical evidence must be compellingly presented.",
  "content": "# Medical Treatment Summary: Comprehensive Narrative Documentation\n\nYou are tasked with creating a sophisticated Medical Treatment Summary that transforms complex medical records into a compelling, legally significant narrative. This document serves as the cornerstone of medical damages presentation in personal injury and medical malpractice litigation, bridging the gap between clinical documentation and persuasive advocacy. Your summary must accomplish three critical objectives simultaneously: maintain rigorous medical accuracy, translate technical information into accessible prose, and build a persuasive narrative that demonstrates the full scope of injury impact on the client's life.\n\n## Strategic Purpose and Audience Considerations\n\nThis document addresses multiple sophisticated audiences with divergent needs. Insurance adjusters require clear causation analysis and medical necessity justification. Defense counsel will scrutinize every causal assertion and treatment decision. Judges need concise, credible medical explanations to rule on motions and admissibility. Juries must understand and emotionally connect with the client's suffering without feeling manipulated by overwrought language. Expert witnesses will rely on your summary as a roadmap for their testimony. Your narrative must therefore balance clinical precision with human storytelling, legal rigor with emotional resonance, and comprehensive detail with readable flow.\n\nThe summary should typically span eight to twenty pages depending on treatment complexity, injury severity, and case duration. Shorter cases involving single incidents with straightforward treatment may warrant concise summaries, while catastrophic injuries requiring years of intervention demand extensive documentation. Every paragraph should advance either the medical narrative, the causation argument, or the damages foundation. Eliminate redundancy while ensuring completeness. The document must stand alone as a comprehensive medical case presentation, yet also complement and reference the detailed medical chronology without duplicating it.\n\n## Establishing the Client's Pre-Incident Baseline\n\nBegin by painting a vivid portrait of who your client was before the incident disrupted their life. Move beyond demographic data to capture the essence of their daily existence, physical capabilities, professional accomplishments, recreational pursuits, and family roles. Search the available documents thoroughly to extract specific details about their occupation, hobbies, athletic activities, caregiving responsibilities, and social engagement. When records indicate the client was a construction supervisor who regularly lifted heavy materials, coached youth soccer, and maintained an active lifestyle hiking with family, these details establish a baseline of robust physical function that makes subsequent limitations more striking.\n\nAddress the client's pre-incident health status with strategic transparency. If medical records reveal a history of lower back pain managed conservatively with occasional chiropractic care, acknowledge this forthrightly while establishing that the client maintained full work capacity and recreational activities despite minor discomfort. This honest foundation prevents defense counsel from characterizing you as concealing relevant history while positioning you to demonstrate how the incident transformed manageable baseline conditions into debilitating impairment. Search historical medical records to identify the frequency, severity, and treatment intensity of any pre-existing conditions, then contrast this with post-incident medical utilization patterns.\n\nQuantify the client's pre-incident functional capacity using specific examples drawn from employment records, hobby documentation, and daily activity descriptions. Rather than stating the client \"was active,\" describe how they worked ten-hour shifts performing physically demanding labor, spent weekends maintaining a large property, and regularly participated in recreational sports leagues. These concrete details establish measurable functional losses when compared against post-injury limitations. The baseline section should leave readers with a clear mental image of a capable, productive individual whose life trajectory was violently disrupted.\n\n## Incident Mechanism and Immediate Injury Presentation\n\nDescribe the traumatic event with sufficient technical detail to establish injury causation while maintaining accessibility for lay readers. When the incident involved a motor vehicle collision, explain the forces involved, the direction of impact, the speed differential, and the specific body mechanics that produced injury. If a client's vehicle was struck from behind at forty-five miles per hour while stopped, causing their head to snap backward then forward violently, this mechanism directly explains cervical spine injuries, traumatic brain injury symptoms, and soft tissue damage. Search accident reports, police records, and engineering analyses to provide accurate incident reconstruction details.\n\nConnect the mechanism of injury directly to the initial symptom presentation and emergency medical response. If the client immediately experienced neck pain, headache, confusion, and upper extremity numbness following the collision, these symptoms align logically with the described mechanism and support diagnoses of cervical strain, concussion, and potential nerve impingement. Detail the emergency medical services response, emergency department evaluation, and initial diagnostic testing with attention to what these early interventions revealed about injury severity. When CT scans, X-rays, or MRI studies were performed emergently, explain what pathology they identified or ruled out, and why certain imaging was medically indicated given the presentation.\n\nAddress any delayed symptom onset with particular care, as defense counsel often exploits treatment gaps to argue against causation. When a client did not seek immediate emergency care but presented to their primary physician three days later with progressively worsening symptoms, explain the medical literature supporting delayed symptom presentation for conditions like soft tissue injuries, concussions, and herniated discs. Search the medical records for provider documentation supporting the causal relationship between the incident and delayed symptoms, including clinical notes stating the symptoms are \"consistent with\" or \"related to\" the described trauma.\n\n## Comprehensive Treatment Narrative and Clinical Rationale\n\nOrganize the treatment course thematically around injury systems and intervention types rather than presenting a simple chronological recitation. Group related treatments together to demonstrate the logical progression from conservative care through increasingly aggressive interventions when initial approaches proved insufficient. Begin with conservative management attempts including medication, physical therapy, injections, and activity modification, explaining the clinical rationale for each approach and the objective measures used to assess effectiveness.\n\nWhen describing pharmaceutical management, specify not just medication names but their therapeutic purposes, dosage escalations, side effects experienced, and effectiveness in controlling symptoms. If the client progressed from over-the-counter anti-inflammatories to prescription NSAIDs to opioid analgesics to nerve pain medications, this escalation demonstrates both increasing pain severity and appropriate stepwise treatment protocols. Search pharmacy records and physician notes to document medication trials, failures, and adjustments, using this progression to demonstrate that pain management needs were genuine and treatment was medically appropriate rather than excessive.\n\nDetail physical therapy and rehabilitation with attention to specific modalities employed, functional goals established, progress achieved, and persistent limitations despite maximal therapeutic effort. When therapy records document that despite twelve weeks of intensive physical therapy three times weekly, the client regained only sixty percent of normal cervical range of motion and continued experiencing daily headaches, this objective documentation supports both the severity of injury and the medical necessity of additional interventions. Search therapy notes for functional capacity assessments, pain scale documentation, and therapist observations about effort level and progress plateaus.\n\nExplain surgical interventions with particular attention to the decision-making process that led to operative treatment. Detail the conservative treatments attempted and failed, the diagnostic studies confirming surgical pathology, the specific procedure performed, the anatomical structures addressed, and the intended therapeutic outcome. When a client underwent cervical fusion surgery, explain that twelve months of conservative care including physical therapy, epidural injections, and medication management failed to provide adequate relief, that MRI studies demonstrated nerve root compression from herniated discs, and that the surgical goal was decompressing neural structures and stabilizing the spine to prevent further deterioration. Search operative reports, pre-surgical consultations, and post-operative notes to provide accurate procedural details and outcome assessments.\n\n## Translating Suffering Into Documented Impact\n\nTransform clinical documentation of pain and limitation into vivid descriptions of how injuries disrupted every aspect of the client's daily existence. Search therapy notes, physician examinations, functional capacity evaluations, and client intake forms for specific examples of activity limitations. Rather than stating the client experienced \"chronic pain,\" describe how they could no longer sleep through the night due to pain awakening them every two hours, required assistance from their spouse to dress each morning because they could not raise their arms overhead, and abandoned their woodworking hobby because they could not tolerate standing or using hand tools for more than fifteen minutes.\n\nQuantify functional losses using objective measures documented in medical records. When physical therapy notes document that cervical range of motion is limited to thirty degrees of rotation compared to the normal eighty degrees, translate this into real-world impact by explaining the client cannot check blind spots while driving, cannot look over their shoulder to interact with passengers, and must turn their entire body to see objects not directly in front of them. Search occupational therapy assessments for activities of daily living limitations, documenting specific tasks the client can no longer perform independently such as bathing, dressing, meal preparation, or household maintenance.\n\nAddress vocational impact with concrete employment documentation. Search personnel records, employer statements, and vocational expert reports to document lost work time, job modifications required, reduced earning capacity, and career trajectory alterations. When the client transitioned from full-time construction supervision to part-time light-duty work at sixty percent of their former income, this represents quantifiable economic damages directly attributable to injury-imposed limitations. Detail any workplace accommodations required, restrictions imposed by treating physicians, and the client's struggle to maintain employment despite significant pain and limitation.\n\nIncorporate psychological and emotional consequences documented by mental health providers. When the client developed depression and anxiety following their injury, search psychiatric records for diagnostic criteria met, symptom severity assessments, medication trials, and therapy participation. Explain how chronic pain, functional limitation, loss of independence, and inability to engage in previously enjoyed activities contributed to psychological deterioration. Connect mental health treatment directly to the physical injuries, demonstrating that psychological suffering represents a foreseeable consequence of the trauma rather than an independent condition.\n\n## Current Status and Future Medical Needs\n\nProvide a clear-eyed assessment of the client's present condition, distinguishing between temporary impairments that may continue improving and permanent limitations that represent the client's new baseline. Search recent medical evaluations, independent medical examinations, and treating provider opinions to establish whether maximum medical improvement has been reached. When providers document that the client has plateaued in their recovery despite optimal treatment, this supports claims for permanent impairment and future medical needs.\n\nDetail ongoing treatment requirements with specificity about frequency, duration, and cost implications. If the client requires pain management injections every three months indefinitely, physical therapy maintenance sessions twice monthly, and daily medication regimens, quantify these needs in terms of annual costs and lifetime projections. Search medical records for provider recommendations regarding future care, including statements about the need for ongoing monitoring, potential future surgical interventions, and permanent activity restrictions.\n\nAddress prognosis with attention to multiple provider opinions, synthesizing consensus views while acknowledging any divergent assessments. When three treating specialists agree the client will experience permanent cervical spine dysfunction requiring lifelong pain management, but an independent medical examiner suggests the client has reached maximum improvement and requires no further treatment, present both perspectives while explaining which opinion is better supported by the objective medical evidence. Search expert reports and deposition testimony to extract specific prognostic statements and their supporting rationale.\n\nDiscuss the potential for future deterioration or additional interventions. When orthopedic surgeons document that the client's spinal fusion will likely lead to adjacent segment degeneration requiring additional surgery within ten to fifteen years, this represents a quantifiable future medical need supported by medical literature and clinical experience. Search medical records for provider discussions of long-term complications, anticipated disease progression, and recommended future monitoring or intervention.\n\n## Medical Necessity and Standard of Care Analysis\n\nAnalyze every significant treatment intervention through the lens of medical necessity and adherence to accepted clinical standards. Search medical literature, clinical practice guidelines, and expert opinions to demonstrate that the care provided aligns with evidence-based protocols for the diagnosed conditions. When treatment choices might appear aggressive or expensive to lay observers, provide clinical justification rooted in the severity of pathology, the failure of conservative approaches, and the alignment with specialty society recommendations.\n\nAddress any treatment gaps or delays proactively before defense counsel exploits them. When a three-month gap exists between physical therapy completion and surgical consultation, search the records to determine whether this delay was medically appropriate (allowing time to assess conservative treatment effectiveness), logistically necessary (waiting for insurance authorization or specialist availability), or potentially problematic. If gaps exist due to the client's financial constraints, insurance coverage issues, or difficulty accessing specialists, document these external barriers while explaining that the delay does not undermine medical necessity.\n\nExplain the reasonableness of medical expenses incurred by connecting costs to the complexity of care required. When surgical costs exceeded one hundred thousand dollars, detail the specific procedures performed, the specialized equipment required, the surgeon's expertise level, and the facility fees associated with complex operative intervention. Search billing records and procedure codes to ensure charges align with the documented services provided and represent fair market value for the geographic region and facility type.\n\n## Causation Framework and Defense Rebuttal\n\nConstruct an airtight causation narrative connecting the incident to every injury claimed and treatment received. Search medical records for provider statements explicitly linking symptoms and diagnoses to the traumatic event, including documentation that injuries are \"consistent with,\" \"caused by,\" or \"directly related to\" the described mechanism. When providers document that the client had no cervical spine complaints in the five years preceding the collision but developed immediate neck pain and subsequent MRI-confirmed disc herniations, the temporal relationship and mechanism support causation.\n\nAddress alternative causation theories preemptively. If the client had prior back pain from degenerative disc disease, distinguish between baseline degenerative changes and traumatic injury by comparing pre-incident and post-incident imaging studies. When new disc herniations appear at levels previously unaffected, or when previously asymptomatic degenerative changes become symptomatic following trauma, explain the medical concept of aggravation of pre-existing conditions. Search medical records for provider opinions distinguishing between degenerative processes and traumatic pathology.\n\nRebut any suggestion that subsequent incidents or intervening causes explain the client's condition. When defense counsel argues that a minor fender-bender six months after the original collision caused the client's ongoing symptoms, search medical records to demonstrate that symptoms were continuous from the original incident, that treatment was ongoing before the subsequent event, and that the minor incident did not produce new pathology or significantly worsen existing conditions. Use treatment chronology and symptom documentation to establish unbroken causation from the original incident through current impairment.\n\n## Synthesis and Damages Foundation\n\nConclude with a powerful integration of the medical narrative that positions the case for optimal damages recovery. Synthesize the journey from pre-incident vitality through traumatic injury, extensive treatment, and permanent impairment into a cohesive story that demonstrates the full scope of harm. Emphasize the most legally significant aspects of the case, whether that involves the severity of initial trauma, the extensiveness of surgical intervention, the permanence of functional limitation, or the ongoing nature of treatment needs and associated costs.\n\nConnect the medical facts to damages categories without overstepping into legal conclusions. Establish the foundation for economic damages by documenting past medical expenses, quantifying future treatment needs, and demonstrating lost earning capacity through vocational impact. Support non-economic damages claims by illustrating pain severity, functional limitation, loss of life enjoyment, and psychological suffering through specific, documented examples rather than hyperbolic characterizations.\n\nProvide the framework for expert testimony by identifying the key medical opinions that support your case theory, the objective evidence underlying those opinions, and the clinical reasoning that connects incident to injury to impairment. Search expert reports to extract the most persuasive statements and ensure your narrative aligns with and supports the opinions your experts will offer at trial.\n\n## Documentation Excellence and Professional Standards\n\nPresent this summary in polished, professional prose that reflects the gravity of the client's experience while maintaining the objectivity expected in legal documentation. Organize content under clear headings that guide readers through the narrative logically, with each section building upon the previous to create a comprehensive understanding. Use topic sentences to introduce each paragraph's central point, followed by supporting evidence drawn from medical records, expert opinions, and documented client experiences.\n\nIntegrate record citations smoothly into the narrative flow rather than using disruptive footnote formats. When referencing specific medical documentation, include sufficient detail for verification\u2014provider name, date of service, and document type\u2014while maintaining readable prose. For example, \"Dr. Sarah Martinez's orthopedic evaluation on March 15, 2024, documented severe cervical spine tenderness, muscle spasm, and restricted range of motion limited to thirty degrees of rotation.\"\n\nMaintain a tone that balances advocacy with credibility. Avoid inflammatory language, exaggeration, or emotional manipulation that undermines professional credibility. Instead, let the documented facts speak powerfully by presenting them clearly and completely. The most persuasive medical summaries allow readers to reach their own conclusions about severity and impact based on comprehensive, well-organized evidence rather than argumentative characterizations.\n\nYour completed Medical Treatment Summary should serve as the definitive medical narrative for the case, educating all audiences about the nature and extent of injuries while building an irrefutable foundation for damages claims. It must withstand rigorous scrutiny from medical experts and opposing counsel while remaining accessible and compelling to the judges and jurors who will ultimately determine the outcome. Through meticulous attention to medical accuracy, strategic organization, and persuasive storytelling, transform complex clinical documentation into a powerful advocacy tool that honors the client's experience and maximizes case value.",
  "parent_skill_id": "38dede99-5114-47a7-9db4-213862152eb3",
  "skill_type": "form",
  "visibility": "public",
  "legal_context": {
    "complexity": "senior",
    "industries": [],
    "party_roles": [
      "plaintiff"
    ],
    "skill_modes": [
      "summarization"
    ],
    "court_systems": [],
    "jurisdictions": [
      "US"
    ],
    "matter_phases": [
      "discovery",
      "pre-trial",
      "trial",
      "settlement"
    ],
    "document_types": [
      "summary"
    ],
    "practice_areas": [
      "Litigation"
    ],
    "sub_practice_areas": [
      "personal-injury"
    ]
  },
  "version": 1,
  "author_name": null,
  "license": "Apache-2.0",
  "created_at": "2026-01-06T03:27:06.057229",
  "updated_at": "2026-02-22T21:37:47.543804"
}